hoard/__init__.py
hoard/api.py
hoard/frontend.py
hoard/main.py
hoard-1.1.1.data/scripts/hoard
hoard-1.1.1.dist-info/DESCRIPTION.rst
hoard-1.1.1.dist-info/entry_points.txt
hoard-1.1.1.dist-info/METADATA
hoard-1.1.1.dist-info/pydist.json
hoard-1.1.1.dist-info/RECORD
hoard-1.1.1.dist-info/top_level.txt
hoard-1.1.1.dist-info/WHEEL
