Metadata-Version: 2.0
Name: hoard
Version: 1.1.1
Summary: UNKNOWN
Home-page: http://github.com/ghickman/hoard-cli
Author: George Hickman
Author-email: george@ghickman.co.uk
License: Copyright (c) 2013 George Hickman
Requires-Dist: requests (==1.1.0)
Requires-Dist: termcolor (==1.1.0)
